mkdocs_pydoc/__init__.py
mkdocs_pydoc/parser.py
mkdocs_pydoc/plugin.py
mkdocs_pydoc-0.1.0.dev0.dist-info/DESCRIPTION.rst
mkdocs_pydoc-0.1.0.dev0.dist-info/METADATA
mkdocs_pydoc-0.1.0.dev0.dist-info/RECORD
mkdocs_pydoc-0.1.0.dev0.dist-info/WHEEL
mkdocs_pydoc-0.1.0.dev0.dist-info/entry_points.txt
mkdocs_pydoc-0.1.0.dev0.dist-info/metadata.json
mkdocs_pydoc-0.1.0.dev0.dist-info/top_level.txt
